cpp_demangle.cpython-310-x86_64-linux-gnu.so
cpp_demangle-0.1.2.dist-info/METADATA
cpp_demangle-0.1.2.dist-info/top_level.txt
cpp_demangle-0.1.2.dist-info/RECORD
cpp_demangle-0.1.2.dist-info/WHEEL
cpp_demangle-0.1.2.dist-info/LICENSE
