Metadata-Version: 2.1
Name: cpp-demangle
Version: 0.1.2
Summary: A package for demangling C++ linker symbols
Home-page: http://github.com/benfred/py-cpp-demangle/
Author: Ben Frederickson
Author-email: ben@benfrederickson.com
License: MIT
Classifier: Development Status :: 3 - Alpha
Classifier: Programming Language :: Python :: 3
Classifier: Intended Audience :: Developers
Classifier: License :: OSI Approved :: MIT License
Classifier: Topic :: Software Development :: Libraries
Classifier: Topic :: Utilities
License-File: LICENSE
